Metadata-Version: 1.1
Name: crm-rfm-modeling
Version: 1.0.1
Summary: RFM (Recency Frequency Monetary) model python package
Home-page: https://github.com/jzarco/RFM
Author: Juan Zarco
Author-email: UNKNOWN
License: GNU General Public License
Platform: UNKNOWN
Classifier: Programming Language :: Python :: 3
Classifier: License :: OSI Approved :: GNU General Public License v3 (GPLv3)
Classifier: Operating System :: OS Independent
Classifier: Development Status :: 4 - Beta
